[{"department":"كلية خدمة المجتمع","allowed-majors":["3230","3214","3210","3209","3206","3205","3203","3202","3201","3086","2836"],"name":"مهارات الحاسب الآلي","section":"522","time":"0900-1029","allowed-colleges":["30","28"],"days":[1,3],"credits":"3","instructor":"علاء عبدالرؤوف عبدالله","code":"3201103","crn":"65229","available":"full"},{"department":"كلية خدمة المجتمع","allowed-majors":["3083"],"name":"مساعد طبيب الاسنان الاكلينكي 1","section":"211","time":"-","allowed-colleges":["30"],"days":[],"credits":"5","instructor":"","code":"3083107","crn":"59619","available":"not-available"},{"department":"موارد بشرية","allowed-majors":["3206"],"name":"الثقافة والسلوك التنظيمي","section":"731","time":"1300-1350","allowed-colleges":["28"],"days":[1,4,3],"credits":"3","instructor":"علي صالح الشبامي","code":"3206102","crn":"64868","available":"not-available"},{"department":"إدارة مالية","allowed-majors":["3203"],"name":"المالية الاسلامية","section":"531","time":"1030-1159","allowed-colleges":["30"],"days":[3,5],"credits":"3","instructor":"محمد احمد حسين البوحمود","code":"3203106","crn":"64905","available":"not-available"},{"department":"موارد بشرية","allowed-majors":["3206"],"name":"إدارة الموارد البشرية","section":"731","time":"1400-1450","allowed-colleges":["28"],"days":[3,2],"credits":"3","instructor":"","code":"3206101","crn":"64867","available":"not-available"},{"department":"كلية خدمة المجتمع","allowed-majors":["3201","2836"],"name":"اللغة الانجليزية (1)","section":"721","time":"1700-1750","allowed-colleges":["30","28"],"days":[1,4,3,2],"credits":"4","instructor":"شهاب احمد المعايطة","code":"3201101","crn":"64717","available":"full"},{"department":"سلاسل الامداد","allowed-majors":["3205"],"name":"ادارة المشتريات والتموين","section":"531","time":"1030-1129","allowed-colleges":["30"],"days":[4,2],"credits":"3","instructor":"محي  الدين  الرحموني","code":"3205105","crn":"64943","available":"not-available"},{"department":"كلية خدمة المجتمع","allowed-majors":["3083"],"name":"علوم الاسنان","section":"211","time":"-","allowed-colleges":["30"],"days":[],"credits":"2","instructor":"","code":"3083104","crn":"59613","available":"not-available"},{"department":"سلاسل الامداد","allowed-majors":["3205"],"name":"إدارة المخزون والمستودعات","section":"521","time":"0730-0859","allowed-colleges":["30"],"days":[4,2],"credits":"3","instructor":"محي  الدين  الرحموني","code":"3205104","crn":"64938","available":"not-available"},{"department":"كلية خدمة المجتمع","allowed-majors":["3230","3214","3210","3209","3206","3205","3203","3202","3201","3086","2836"],"name":"مهارات الحاسب الآلي","section":"524","time":"0900-1029","allowed-colleges":["30","28"],"days":[4,2],"credits":"3","instructor":"علاء عبدالرؤوف عبدالله","code":"3201103","crn":"65230","available":"full"},{"department":"كلية خدمة المجتمع","allowed-majors":["3230","3223","3222","3221","3220","3214","3210","3209","3206","3205","3203","3202","3201","2836"],"name":"المهارات الحياتية","section":"525","time":"1100-1259","allowed-colleges":["30","28"],"days":[5],"credits":"2","instructor":"مروان عبدالرحمن الدحيلان","code":"3201102","crn":"65243","available":"available"},{"department":"برمجة تطبيقات الويب","allowed-majors":["3223","3222","3221","3220","3201"],"name":"اساسيات الحاسب والبرمجة","section":"522","time":"0730-0859","allowed-colleges":["30","28"],"days":[1,3],"credits":"3","instructor":"علاء عبدالرؤوف عبدالله","code":"3220101","crn":"65225","available":"full"},{"department":"كلية خدمة المجتمع","allowed-majors":["3004","3003","3002"],"name":"تصميم التقارير","section":"121","time":"-","allowed-colleges":["30"],"days":[],"credits":"2","instructor":"","code":"3053103","crn":"53220","available":"not-available"},{"department":"إدارة مالية","allowed-majors":["3203"],"name":"منشات وأسواق مالية","section":"531","time":"1230-1359","allowed-colleges":["30"],"days":[1],"credits":"3","instructor":"محمد احمد حسين البوحمود","code":"3203101","crn":"64903","available":"not-available"},{"department":"كلية خدمة المجتمع","allowed-majors":["3083"],"name":"المصطلحات في طب الاسنان","section":"211","time":"-","allowed-colleges":["30"],"days":[],"credits":"1","instructor":"","code":"3083103","crn":"59611","available":"not-available"},{"department":"كلية خدمة المجتمع","allowed-majors":["3086","2836","3214","3209","3206","3205","3203","3202","3201"],"name":"مبادئ المحاسبة والتقرير المالي","section":"521","time":"1030-1229","allowed-colleges":["30","28"],"days":[4,2],"credits":"4","instructor":"محمد آدم محمد هارون","code":"3201105","crn":"65251","available":"full"},{"department":"برمجة تطبيقات الويب","allowed-majors":["3223","3222","3221","3220","3201"],"name":"اساسيات الرياضيات والاحصاء","section":"522","time":"0900-1029","allowed-colleges":["30","28"],"days":[4,2],"credits":"3","instructor":"ياسر محمد عياد سليمان","code":"3220102","crn":"65254","available":"available"},{"department":"كلية خدمة المجتمع","allowed-majors":["3201","2836"],"name":"مقدمة في  الادارة","section":"721","time":"1700-1750","allowed-colleges":["30","28"],"days":[4,5],"credits":"3","instructor":"","code":"3201106","crn":"64721","available":"full"},{"department":"كلية خدمة المجتمع","allowed-majors":["3002"],"name":"محاسبة متوسطة","section":"121","time":"-","allowed-colleges":[],"days":[],"credits":"3","instructor":"","code":"3040140","crn":"51281","available":"not-available"},{"department":"موارد بشرية","allowed-majors":["3206"],"name":"إعدادتصميم أنظمةالاجوروالحوافز","section":"731","time":"1600-1650","allowed-colleges":["28"],"days":[1,2],"credits":"3","instructor":"","code":"3206104","crn":"64870","available":"not-available"},{"department":"كلية خدمة المجتمع","allowed-majors":["3230","3223","3222","3221","3220","3214","3210","3209","3206","3205","3203","3202","3201","2836"],"name":"المهارات الحياتية","section":"522","time":"1100-1259","allowed-colleges":["30","28"],"days":[5],"credits":"2","instructor":"عبدالاله  الدريويش","code":"3201102","crn":"65249","available":"available"},{"department":"كلية خدمة المجتمع","allowed-majors":["3230","3223","3222","3221","3220","3214","3210","3209","3206","3205","3203","3202","3201","2836"],"name":"المهارات الحياتية","section":"527","time":"1030-1229","allowed-colleges":["30","28"],"days":[2],"credits":"2","instructor":"عبدالاله  الدريويش","code":"3201102","crn":"65246","available":"full"},{"department":"كلية خدمة المجتمع","allowed-majors":["3214","3206","3205","3203","3202","3201","3086","2836"],"name":"أساسيات الرياضيات والاحصاء","section":"521","time":"0730-0859","allowed-colleges":["30","28"],"days":[1,3],"credits":"3","instructor":"ياسر محمد عياد سليمان","code":"3201108","crn":"65252","available":"full"},{"department":"كلية خدمة المجتمع","allowed-majors":["3223","3222","3221","3220","3214","3210","3206","3205","3203","3202","3201","2836"],"name":"اللغة الانجليزية (1)","section":"522","time":"0730-0859","allowed-colleges":["30","28"],"days":[1,4,3,2],"credits":"4","instructor":"","code":"3201101","crn":"65220","available":"available"},{"department":"كلية خدمة المجتمع","allowed-majors":["3201","2836"],"name":"مهارات الحاسب الآلي","section":"731","time":"1400-1450","allowed-colleges":["30","28"],"days":[1,3],"credits":"3","instructor":"ذي يزن حسن","code":"3201103","crn":"64762","available":"not-available"},{"department":"كلية خدمة المجتمع","allowed-majors":["3230","3214","3210","3209","3206","3205","3203","3202","3201","3086","2836"],"name":"مهارات الحاسب الآلي","section":"521","time":"0900-1029","allowed-colleges":["30","28"],"days":[1,3],"credits":"3","instructor":"منصور راتب  محمد عبيدات","code":"3201103","crn":"65234","available":"full"},{"department":"كلية خدمة المجتمع","allowed-majors":["3201","2836"],"name":"مهارات الحاسب الآلي","section":"721","time":"1300-1350","allowed-colleges":["30","28"],"days":[1,3],"credits":"3","instructor":"ذي يزن حسن","code":"3201103","crn":"64719","available":"full"},{"department":"هندسة الري","allowed-majors":["3230"],"name":"اقتصاد وارشاد مائي","section":"521","time":"1030-1229","allowed-colleges":["30","28"],"days":[4],"credits":"2","instructor":"فهد محمد الزهراني","code":"3230104","crn":"65346","available":"available"},{"department":"سلاسل الامداد","allowed-majors":["3205"],"name":"مبادئ إدارة سلاسل الامداد","section":"521","time":"0730-0859","allowed-colleges":["30","28"],"days":[1,3],"credits":"3","instructor":"ماجد عباس البوعويس","code":"3205101","crn":"64928","available":"not-available"},{"department":"كلية خدمة المجتمع","allowed-majors":["3230","3210","3209","3201"],"name":"لغة انجليزية (1)","section":"522","time":"1230-1359","allowed-colleges":["30","28"],"days":[2],"credits":"3","instructor":"","code":"3201110","crn":"65223","available":"full"},{"department":"كلية خدمة المجتمع","allowed-majors":["3230","3214","3210","3209","3206","3205","3203","3202","3201","2836"],"name":"مهارات الحاسب الآلي","section":"528","time":"1230-1359","allowed-colleges":["30","28"],"days":[4,2],"credits":"3","instructor":"عمر فراج الرحيلي","code":"3201103","crn":"65233","available":"available"},{"department":"كلية خدمة المجتمع","allowed-majors":["3223","3222","3221","3220","3214","3210","3206","3205","3203","3202","3201","3086","2836"],"name":"اللغة الانجليزية (1)","section":"523","time":"0730-0859","allowed-colleges":["30","28"],"days":[1,4,3,2],"credits":"4","instructor":"","code":"3201101","crn":"65219","available":"full"},{"department":"موارد بشرية","allowed-majors":["3206"],"name":"الثقافة والسلوك التنظيمي","section":"721","time":"1300-1350","allowed-colleges":["28"],"days":[1,4,3],"credits":"3","instructor":"علي صالح الشبامي","code":"3206102","crn":"64854","available":"not-available"},{"department":"سلاسل الامداد","allowed-majors":["3205"],"name":"إدارة المخزون والمستودعات","section":"531","time":"0730-0859","allowed-colleges":["30"],"days":[4,2],"credits":"3","instructor":"محي  الدين  الرحموني","code":"3205104","crn":"64939","available":"not-available"},{"department":"سلاسل الامداد","allowed-majors":["3205"],"name":"ادارة النقل والتوزيع","section":"521","time":"0900-1029","allowed-colleges":["30"],"days":[1,3],"credits":"3","instructor":"محي  الدين  الرحموني","code":"3205103","crn":"64940","available":"not-available"},{"department":"موارد بشرية","allowed-majors":["3206"],"name":"إدارة الموارد البشرية","section":"721","time":"1300-1350","allowed-colleges":["28"],"days":[3,2],"credits":"3","instructor":"","code":"3206101","crn":"64853","available":"not-available"},{"department":"كلية خدمة المجتمع","allowed-majors":["3201","2836"],"name":"مقدمة في  الادارة","section":"731","time":"1400-1450","allowed-colleges":["30","28"],"days":[4,5],"credits":"3","instructor":"","code":"3201106","crn":"64764","available":"not-available"},{"department":"كلية خدمة المجتمع","allowed-majors":["3230","3210","3209"],"name":"لغة انجليزية (1)","section":"521","time":"1230-1359","allowed-colleges":["30","28"],"days":[1,3],"credits":"3","instructor":"","code":"3201110","crn":"65222","available":"available"},{"department":"كلية خدمة المجتمع","allowed-majors":["3002"],"name":"محاسبة التكاليف (1)","section":"121","time":"-","allowed-colleges":[],"days":[],"credits":"3","instructor":"","code":"3040139","crn":"51280","available":"not-available"},{"department":"كلية خدمة المجتمع","allowed-majors":["3083"],"name":"مهارات التواصل واخلاق المهنة","section":"211","time":"-","allowed-colleges":["30"],"days":[],"credits":"1","instructor":"","code":"3083105","crn":"59615","available":"not-available"},{"department":"موارد بشرية","allowed-majors":["3206"],"name":"تخطيط الموارد البشرية","section":"721","time":"1600-1650","allowed-colleges":["28"],"days":[3,2],"credits":"3","instructor":"علي صالح الشبامي","code":"3206106","crn":"64858","available":"not-available"},{"department":"كلية خدمة المجتمع","allowed-majors":["3214","3209","3206","3205","3203","3202","3201","3086","2836"],"name":"مبادئ المحاسبة والتقرير المالي","section":"522","time":"1030-1229","allowed-colleges":["30","28"],"days":[3,5],"credits":"4","instructor":"علي حبيب حسن الحسين","code":"3201105","crn":"65250","available":"full"},{"department":"كلية خدمة المجتمع","allowed-majors":["3004"],"name":"إدارة الإنتاج","section":"121","time":"-","allowed-colleges":[],"days":[],"credits":"3","instructor":"","code":"3040136","crn":"60159","available":"not-available"},{"department":"برمجة تطبيقات الويب","allowed-majors":["3223","3222","3221","3220","3201"],"name":"اساسيات قواعد البيانات","section":"524","time":"1030-1229","allowed-colleges":["30","28"],"days":[1,3],"credits":"4","instructor":"علاء عبدالرؤوف عبدالله","code":"3220103","crn":"65227","available":"full"},{"department":"برمجة تطبيقات الويب","allowed-majors":["3223","3222","3221","3220","3201"],"name":"اساسيات قواعد البيانات","section":"522","time":"1030-1229","allowed-colleges":["30","28"],"days":[4,2],"credits":"4","instructor":"علاء عبدالرؤوف عبدالله","code":"3220103","crn":"65228","available":"full"},{"department":"كلية خدمة المجتمع","allowed-majors":["3002"],"name":"استخدامات الحاسب في المحاسبة E","section":"121","time":"0730-0859","allowed-colleges":["30"],"days":[1,3],"credits":"3","instructor":"علي حبيب حسن الحسين","code":"3040151","crn":"64777","available":"not-available"},{"department":"كلية خدمة المجتمع","allowed-majors":["3004","3003","3002"],"name":"مبادئ الاحصاء (1)","section":"121","time":"0900-1029","allowed-colleges":["30"],"days":[1,3],"credits":"2","instructor":"ياسر محمد عياد سليمان","code":"3040126","crn":"64772","available":"not-available"},{"department":"كلية خدمة المجتمع","allowed-majors":["3201","2836"],"name":"مبادئ المحاسبة والتقرير المالي","section":"721","time":"1500-1550","allowed-colleges":["30","28"],"days":[1,4,2],"credits":"4","instructor":"علي صالح الشبامي","code":"3201105","crn":"64720","available":"full"},{"department":"موارد بشرية","allowed-majors":["3206"],"name":"تنمية مهارات أخصائي مواردبشرية","section":"721","time":"1400-1450","allowed-colleges":["28"],"days":[1,4],"credits":"3","instructor":"","code":"3206105","crn":"64857","available":"not-available"},{"department":"سلاسل الامداد","allowed-majors":["3205"],"name":"إدارة الانتاج والعمليات","section":"521","time":"0900-1029","allowed-colleges":["30"],"days":[4,2],"credits":"3","instructor":"ماجد عباس البوعويس","code":"3205102","crn":"64930","available":"not-available"},{"department":"كلية خدمة المجتمع","allowed-majors":["3083"],"name":"علم مواد الاسنان","section":"211","time":"-","allowed-colleges":["30"],"days":[],"credits":"2","instructor":"","code":"3083108","crn":"59621","available":"not-available"},{"department":"كلية خدمة المجتمع","allowed-majors":["3230","3223","3222","3221","3220","3214","3210","3209","3206","3205","3203","3202","3201","2836"],"name":"المهارات الحياتية","section":"521","time":"0900-1059","allowed-colleges":["30","28"],"days":[5],"credits":"2","instructor":"عبدالاله  الدريويش","code":"3201102","crn":"65248","available":"full"},{"department":"كلية خدمة المجتمع","allowed-majors":["3214","3206","3205","3203","3202","3086","2836"],"name":"أساسيات الرياضيات والاحصاء","section":"522","time":"0730-0859","allowed-colleges":["30","28"],"days":[4,2],"credits":"3","instructor":"ياسر محمد عياد سليمان","code":"3201108","crn":"65253","available":"full"},{"department":"هندسة الري","allowed-majors":["3230"],"name":"اساسيات التربةواستصلاح الاراضي","section":"521","time":"0900-1029","allowed-colleges":["30","28"],"days":[4,2],"credits":"3","instructor":"محمد احمد السند","code":"3230103","crn":"65345","available":"available"},{"department":"كلية خدمة المجتمع","allowed-majors":["3201","2836"],"name":"المهارات الحياتية","section":"731","time":"1300-1350","allowed-colleges":["30","28"],"days":[4,2],"credits":"2","instructor":"متعب مسفر القثامي","code":"3201102","crn":"64761","available":"not-available"},{"department":"كلية خدمة المجتمع","allowed-majors":["3004","3003","3002"],"name":"تصميم النماذج","section":"121","time":"-","allowed-colleges":[],"days":[],"credits":"3","instructor":"","code":"3053102","crn":"53219","available":"not-available"},{"department":"كلية خدمة المجتمع","allowed-majors":["3223","3222","3221","3220","3214","3210","3206","3205","3203","3202","3201","2836"],"name":"اللغة الانجليزية (1)","section":"521","time":"0730-0859","allowed-colleges":["30","28"],"days":[1,4,3,2],"credits":"4","instructor":"","code":"3201101","crn":"65218","available":"full"},{"department":"برمجة تطبيقات الويب","allowed-majors":["3223","3222","3221","3220","3201"],"name":"اساسيات الحاسب والبرمجة","section":"521","time":"0730-0859","allowed-colleges":["30","28"],"days":[1,3],"credits":"3","instructor":"منصور راتب  محمد عبيدات","code":"3220101","crn":"65236","available":"full"},{"department":"كلية خدمة المجتمع","allowed-majors":["3230","3210","3209","3201"],"name":"لغة انجليزية (1)","section":"523","time":"0900-1029","allowed-colleges":["30","28"],"days":[5],"credits":"3","instructor":"","code":"3201110","crn":"65221","available":"available"},{"department":"كلية خدمة المجتمع","allowed-majors":["3201","2836"],"name":"مبادئ المحاسبة والتقرير المالي","section":"731","time":"1500-1550","allowed-colleges":["30","28"],"days":[1,4,2],"credits":"4","instructor":"علي صالح الشبامي","code":"3201105","crn":"64763","available":"not-available"},{"department":"كلية خدمة المجتمع","allowed-majors":["3214","3210","3209","3206","3205","3203","3202","3201","2836"],"name":"مقدمة في  الادارة","section":"521","time":"1030-1159","allowed-colleges":["30","28"],"days":[1,3],"credits":"3","instructor":"ماجد عباس البوعويس","code":"3201106","crn":"65245","available":"full"},{"department":"سلاسل الامداد","allowed-majors":["3205"],"name":"موضوعات مختارةفي سلاسل الامداد","section":"521","time":"1030-1159","allowed-colleges":["30"],"days":[1,3],"credits":"3","instructor":"محمد نصر محمد سعيد","code":"3205106","crn":"64926","available":"not-available"},{"department":"كلية خدمة المجتمع","allowed-majors":["3230","3223","3222","3221","3220","3214","3210","3209","3206","3205","3203","3202","3201","2836"],"name":"المهارات الحياتية","section":"526","time":"1030-1229","allowed-colleges":["30","28"],"days":[4],"credits":"2","instructor":"عبدالاله  الدريويش","code":"3201102","crn":"65247","available":"available"},{"department":"كلية خدمة المجتمع","allowed-majors":["3230","3223","3222","3221","3220","3214","3210","3209","3206","3205","3203","3202","3201","3086","2836"],"name":"المهارات الحياتية","section":"524","time":"1030-1229","allowed-colleges":["30","28"],"days":[1],"credits":"2","instructor":"مروان عبدالرحمن الدحيلان","code":"3201102","crn":"65241","available":"full"},{"department":"كلية خدمة المجتمع","allowed-majors":["3230","3214","3210","3209","3206","3205","3203","3202","3201","2836"],"name":"مهارات الحاسب الآلي","section":"525","time":"0900-1029","allowed-colleges":["30","28"],"days":[5],"credits":"3","instructor":"علاء عبدالرؤوف عبدالله","code":"3201103","crn":"65231","available":"available"},{"department":"كلية خدمة المجتمع","allowed-majors":["3230","3214","3210","3209","3206","3205","3203","3202","3201","3086","2836"],"name":"مهارات الحاسب الآلي","section":"523","time":"0900-1029","allowed-colleges":["30","28"],"days":[4,2],"credits":"3","instructor":"منصور راتب  محمد عبيدات","code":"3201103","crn":"65235","available":"full"},{"department":"موارد بشرية","allowed-majors":["3206"],"name":"طرق تحليل وتصنيف الوظائف","section":"731","time":"1500-1550","allowed-colleges":["28"],"days":[4,3],"credits":"3","instructor":"علي صالح الشبامي","code":"3206103","crn":"64869","available":"not-available"},{"department":"كلية خدمة المجتمع","allowed-majors":["3083"],"name":"مكافحة العدوى","section":"211","time":"-","allowed-colleges":["30"],"days":[],"credits":"1","instructor":"","code":"3083102","crn":"59609","available":"not-available"},{"department":"سلاسل الامداد","allowed-majors":["3205"],"name":"مبادئ إدارة سلاسل الامداد","section":"531","time":"0730-0859","allowed-colleges":["30"],"days":[1,3],"credits":"3","instructor":"ماجد عباس البوعويس","code":"3205101","crn":"64929","available":"not-available"},{"department":"كلية خدمة المجتمع","allowed-majors":["3003"],"name":"ادارة وتقييم قواعد البيانات","section":"121","time":"-","allowed-colleges":["30"],"days":[],"credits":"3","instructor":"","code":"3040153","crn":"55796","available":"not-available"},{"department":"كلية خدمة المجتمع","allowed-majors":["3002"],"name":"محاسبة المنشات المالية","section":"121","time":"1030-1159","allowed-colleges":["30"],"days":[4,2],"credits":"3","instructor":"علي حبيب حسن الحسين","code":"3040149","crn":"64716","available":"not-available"},{"department":"كلية خدمة المجتمع","allowed-majors":["3083"],"name":"اساسيات مساعد طبيب اسنان","section":"211","time":"-","allowed-colleges":["30"],"days":[],"credits":"2","instructor":"","code":"3083101","crn":"59607","available":"not-available"},{"department":"كلية خدمة المجتمع","allowed-majors":["3230","3214","3210","3209","3206","3205","3203","3202","3201","2836"],"name":"مهارات الحاسب الآلي","section":"527","time":"1230-1359","allowed-colleges":["30","28"],"days":[1,3],"credits":"3","instructor":"عمر فراج الرحيلي","code":"3201103","crn":"65232","available":"full"},{"department":"كلية خدمة المجتمع","allowed-majors":["3002"],"name":"محاسبة شركات (2)","section":"121","time":"1400-1559","allowed-colleges":[],"days":[3],"credits":"2","instructor":"محمد آدم محمد هارون","code":"3040142","crn":"64715","available":"not-available"},{"department":"موارد بشرية","allowed-majors":["3206"],"name":"إعدادتصميم أنظمةالاجوروالحوافز","section":"721","time":"1700-1750","allowed-colleges":["30","28"],"days":[1,2],"credits":"3","instructor":"","code":"3206104","crn":"64856","available":"not-available"},{"department":"كلية خدمة المجتمع","allowed-majors":["3201","2836"],"name":"اللغة الانجليزية (1)","section":"731","time":"1500-1550","allowed-colleges":["30","28"],"days":[1,4,3,2],"credits":"4","instructor":"شهاب احمد المعايطة","code":"3201101","crn":"64760","available":"not-available"},{"department":"إدارة مالية","allowed-majors":["3203"],"name":"الاستثمار","section":"521","time":"0900-1029","allowed-colleges":["30"],"days":[1,4],"credits":"3","instructor":"ابراهيم عمر الامين","code":"3203103","crn":"64886","available":"not-available"},{"department":"الماحاسبة","allowed-majors":["3202"],"name":"المحاسبة المتوسطة (1)","section":"521","time":"0900-1029","allowed-colleges":["30"],"days":[4,2],"credits":"3","instructor":"محمد آدم محمد هارون","code":"3202104","crn":"64847","available":"available"},{"department":"إدارة مالية","allowed-majors":["3203"],"name":"منشات وأسواق مالية","section":"521","time":"1230-1359","allowed-colleges":["30"],"days":[1],"credits":"3","instructor":"محمد احمد حسين البوحمود","code":"3203101","crn":"64902","available":"not-available"},{"department":"هندسة الري","allowed-majors":["3230"],"name":"الرياضيات العامة والإحصاء","section":"521","time":"1030-1159","allowed-colleges":["30","28"],"days":[1,3],"credits":"3","instructor":"احمد جمال محمد العرفج","code":"3230101","crn":"65256","available":"available"},{"department":"برمجة تطبيقات الويب","allowed-majors":["3223","3222","3221","3220","3201"],"name":"اساسيات قواعد البيانات","section":"521","time":"1030-1229","allowed-colleges":["30","28"],"days":[4,2],"credits":"4","instructor":"منصور راتب  محمد عبيدات","code":"3220103","crn":"65239","available":"full"},{"department":"إدارة مالية","allowed-majors":["3203"],"name":"الاستثمار","section":"531","time":"0900-1029","allowed-colleges":["30"],"days":[1,4],"credits":"3","instructor":"ابراهيم عمر الامين","code":"3203103","crn":"64887","available":"not-available"},{"department":"إدارة مالية","allowed-majors":["3203"],"name":"مالية الشركات","section":"531","time":"0730-0859","allowed-colleges":["30"],"days":[3,5],"credits":"3","instructor":"محمد احمد حسين البوحمود","code":"3203102","crn":"64901","available":"not-available"},{"department":"إدارة مالية","allowed-majors":["3203"],"name":"تحليل التقاريروالقوائم المالية","section":"531","time":"0730-0859","allowed-colleges":["30"],"days":[1,4],"credits":"3","instructor":"ابراهيم عمر الامين","code":"3203105","crn":"64852","available":"not-available"},{"department":"برمجة تطبيقات الويب","allowed-majors":["3223","3222","3221","3220","3201"],"name":"اساسيات الرياضيات والاحصاء","section":"521","time":"0900-1029","allowed-colleges":["30","28"],"days":[1,3],"credits":"3","instructor":"احمد جمال محمد العرفج","code":"3220102","crn":"65255","available":"full"},{"department":"برمجة تطبيقات الويب","allowed-majors":["3223","3222","3221","3220","3201"],"name":"اساسيات الحاسب والبرمجة","section":"523","time":"0730-0859","allowed-colleges":["30","28"],"days":[4,2],"credits":"3","instructor":"منصور راتب  محمد عبيدات","code":"3220101","crn":"65237","available":"available"},{"department":"موارد بشرية","allowed-majors":["3206"],"name":"طرق تحليل وتصنيف الوظائف","section":"721","time":"1500-1550","allowed-colleges":["28"],"days":[4,3],"credits":"3","instructor":"علي صالح الشبامي","code":"3206103","crn":"64855","available":"not-available"},{"department":"الماحاسبة","allowed-majors":["3202"],"name":"أساسيات محاسبة اداريةوالتكاليف","section":"521","time":"1030-1159","allowed-colleges":["30"],"days":[4,2],"credits":"3","instructor":"عيد عوض حسن","code":"3202102","crn":"64849","available":"available"},{"department":"كلية خدمة المجتمع","allowed-majors":["3002"],"name":"محاسبة شركات (1)","section":"121","time":"-","allowed-colleges":[],"days":[],"credits":"2","instructor":"","code":"3040141","crn":"55801","available":"not-available"},{"department":"موارد بشرية","allowed-majors":["3206"],"name":"تخطيط الموارد البشرية","section":"731","time":"1500-1550","allowed-colleges":["28"],"days":[3,2],"credits":"3","instructor":"علي صالح الشبامي","code":"3206106","crn":"64872","available":"not-available"},{"department":"برمجة تطبيقات الويب","allowed-majors":["3223","3222","3221","3220","3201"],"name":"اساسيات الحاسب والبرمجة","section":"524","time":"0730-0859","allowed-colleges":["30","28"],"days":[4,2],"credits":"3","instructor":"علاء عبدالرؤوف عبدالله","code":"3220101","crn":"65226","available":"full"},{"department":"كلية خدمة المجتمع","allowed-majors":["3004"],"name":"مفاهيم ادارة الأعمال","section":"121","time":"-","allowed-colleges":[],"days":[],"credits":"2","instructor":"","code":"3040137","crn":"51273","available":"not-available"},{"department":"سلاسل الامداد","allowed-majors":["3205"],"name":"إدارة الانتاج والعمليات","section":"531","time":"0900-1029","allowed-colleges":["30"],"days":[4,2],"credits":"3","instructor":"ماجد عباس البوعويس","code":"3205102","crn":"64931","available":"not-available"},{"department":"سلاسل الامداد","allowed-majors":["3205"],"name":"موضوعات مختارةفي سلاسل الامداد","section":"531","time":"1030-1159","allowed-colleges":["30"],"days":[1,3],"credits":"3","instructor":"محمد نصر محمد سعيد","code":"3205106","crn":"64927","available":"not-available"},{"department":"كلية خدمة المجتمع","allowed-majors":["3003"],"name":"لغات الحاسب الآلي (2)","section":"121","time":"-","allowed-colleges":["30"],"days":[],"credits":"3","instructor":"","code":"3040155","crn":"60161","available":"not-available"},{"department":"كلية خدمة المجتمع","allowed-majors":["3230","3214","3210","3209","3206","3205","3203","3202","3201","2836"],"name":"مهارات الحاسب الآلي","section":"526","time":"1230-1359","allowed-colleges":["30","28"],"days":[1,3],"credits":"3","instructor":"منصور راتب  محمد عبيدات","code":"3201103","crn":"65240","available":"full"},{"department":"برمجة تطبيقات الويب","allowed-majors":["3223","3222","3221","3220","3201"],"name":"اساسيات قواعد البيانات","section":"523","time":"1030-1229","allowed-colleges":["30","28"],"days":[1,3],"credits":"4","instructor":"منصور راتب  محمد عبيدات","code":"3220103","crn":"65238","available":"available"},{"department":"كلية خدمة المجتمع","allowed-majors":["3230","3223","3222","3221","3220","3214","3210","3209","3206","3205","3203","3202","3201","3086","2836"],"name":"المهارات الحياتية","section":"523","time":"0900-1059","allowed-colleges":["30","28"],"days":[5],"credits":"2","instructor":"مروان عبدالرحمن الدحيلان","code":"3201102","crn":"65242","available":"full"},{"department":"الماحاسبة","allowed-majors":["3202"],"name":"محاسبة الزكاة والضرائب","section":"521","time":"0900-1029","allowed-colleges":["30"],"days":[1,3],"credits":"3","instructor":"علي حبيب حسن الحسين","code":"3202103","crn":"64850","available":"available"},{"department":"كلية خدمة المجتمع","allowed-majors":["3003"],"name":"تصميم قواعد البيانات","section":"121","time":"-","allowed-colleges":["30"],"days":[],"credits":"3","instructor":"","code":"3040144","crn":"55798","available":"not-available"},{"department":"هندسة الري","allowed-majors":["3230"],"name":"أساسيات هيدرولوجياقياسات حقلية","section":"521","time":"1030-1229","allowed-colleges":["30","28"],"days":[2],"credits":"2","instructor":"عبدالحليم  عبدالله","code":"3230102","crn":"65344","available":"available"},{"department":"إدارة مالية","allowed-majors":["3203"],"name":"تحليل التقاريروالقوائم المالية","section":"521","time":"0730-0859","allowed-colleges":["30"],"days":[1,4],"credits":"3","instructor":"ابراهيم عمر الامين","code":"3203105","crn":"64851","available":"not-available"},{"department":"الماحاسبة","allowed-majors":["3202"],"name":"المحاسبة الحكومية","section":"521","time":"0800-0859","allowed-colleges":["30"],"days":[1,3],"credits":"2","instructor":"محمد آدم محمد هارون","code":"3202105","crn":"64846","available":"available"},{"department":"إدارة مالية","allowed-majors":["3203"],"name":"مالية الشركات","section":"521","time":"0730-0859","allowed-colleges":["30"],"days":[3,5],"credits":"3","instructor":"محمد احمد حسين البوحمود","code":"3203102","crn":"64900","available":"not-available"},{"department":"سلاسل الامداد","allowed-majors":["3205"],"name":"ادارة المشتريات والتموين","section":"521","time":"1030-1159","allowed-colleges":["30"],"days":[4,2],"credits":"3","instructor":"محي  الدين  الرحموني","code":"3205105","crn":"64942","available":"not-available"},{"department":"إدارة مالية","allowed-majors":["3203"],"name":"المالية الاسلامية","section":"521","time":"1030-1159","allowed-colleges":["30"],"days":[3,5],"credits":"3","instructor":"محمد احمد حسين البوحمود","code":"3203106","crn":"64904","available":"not-available"},{"department":"كلية خدمة المجتمع","allowed-majors":["3083"],"name":"علم الاشعة","section":"211","time":"-","allowed-colleges":["30"],"days":[],"credits":"2","instructor":"","code":"3083106","crn":"59617","available":"not-available"},{"department":"كلية خدمة المجتمع","allowed-majors":["3214","3210","3209","3206","3205","3203","3202","3201","2836"],"name":"مقدمة في  الادارة","section":"522","time":"0900-1029","allowed-colleges":["30","28"],"days":[4,2],"credits":"3","instructor":"محمد نصر محمد سعيد","code":"3201106","crn":"65244","available":"available"},{"department":"كلية خدمة المجتمع","allowed-majors":["3201","2836"],"name":"المهارات الحياتية","section":"721","time":"1300-1350","allowed-colleges":["30","28"],"days":[4,2],"credits":"2","instructor":"متعب مسفر القثامي","code":"3201102","crn":"64718","available":"full"},{"department":"كلية خدمة المجتمع","allowed-majors":["3223","3222","3221","3220","3214","3210","3206","3205","3203","3202","3201","3086","2836"],"name":"اللغة الانجليزية (1)","section":"524","time":"1030-1229","allowed-colleges":["30","28"],"days":[1,4,3,2],"credits":"4","instructor":"","code":"3201101","crn":"65224","available":"full"},{"department":"موارد بشرية","allowed-majors":["3206"],"name":"تنمية مهارات أخصائي مواردبشرية","section":"731","time":"1400-1450","allowed-colleges":["28"],"days":[1,4],"credits":"3","instructor":"","code":"3206105","crn":"64871","available":"not-available"},{"department":"كلية خدمة المجتمع","allowed-majors":["3003"],"name":"نظم ادارة مكتبية","section":"121","time":"-","allowed-colleges":["30"],"days":[],"credits":"2","instructor":"","code":"3040154","crn":"60160","available":"not-available"},{"department":"كلية خدمة المجتمع","allowed-majors":["3083"],"name":"تدبير المرضى والوقاية","section":"211","time":"-","allowed-colleges":["30"],"days":[],"credits":"1","instructor":"","code":"3083109","crn":"59623","available":"not-available"},{"department":"الماحاسبة","allowed-majors":["3202"],"name":"اخصائي ضريبة القيمةالمضافة VAT","section":"521","time":"1030-1229","allowed-colleges":["30"],"days":[1,3],"credits":"4","instructor":"محمد آدم محمد هارون","code":"3202106","crn":"64848","available":"available"},{"department":"إدارة مالية","allowed-majors":["3203"],"name":"المشتقات المالية","section":"521","time":"0900-1029","allowed-colleges":["30","28"],"days":[3,5],"credits":"3","instructor":"","code":"3203104","crn":"65327","available":"not-available"},{"department":"الماحاسبة","allowed-majors":["3202"],"name":"تطبيقات الحاسب في المحاسبة","section":"521","time":"0730-0859","allowed-colleges":["30","28"],"days":[4,2],"credits":"3","instructor":"علي حبيب حسن الحسين","code":"3202101","crn":"65324","available":"available"}]